[{"id":-0,"variable":"part_id","value":"2111931"},{"id":-1,"variable":"part_id","value":"2111937"},{"id":1,"variable":"part_id","value":"2112076"},{"id":2,"variable":"part_id","value":"2112081"},{"id":3,"variable":"part_id","value":"2112086"},{"id":-2,"variable":"part_id","value":"2112116"},{"id":4,"variable":"part_id","value":"2112126"},{"id":5,"variable":"part_id","value":"2112141"},{"id":6,"variable":"part_id","value":"2112151"},{"id":-3,"variable":"part_id","value":"2112161"},{"id":7,"variable":"part_id","value":"2112166"},{"id":8,"variable":"part_id","value":"2112186"},{"id":9,"variable":"part_id","value":"2112206"},{"id":-0,"variable":"parent_id","value":"0"},{"id":-1,"variable":"parent_id","value":"2111931"},{"id":1,"variable":"parent_id","value":"2111937"},{"id":2,"variable":"parent_id","value":"2111937"},{"id":3,"variable":"parent_id","value":"2111937"},{"id":-2,"variable":"parent_id","value":"2111931"},{"id":4,"variable":"parent_id","value":"2112116"},{"id":5,"variable":"parent_id","value":"2112116"},{"id":6,"variable":"parent_id","value":"2112116"},{"id":-3,"variable":"parent_id","value":"2111931"},{"id":7,"variable":"parent_id","value":"2112161"},{"id":8,"variable":"parent_id","value":"2112161"},{"id":9,"variable":"parent_id","value":"2112161"},{"id":-0,"variable":"title","value":"Simplifiez vos réunions grâce au Doodling"},{"id":-1,"variable":"title","value":"Découvrir les bases du Doodling"},{"id":1,"variable":"title","value":"Introduction au Doodling"},{"id":2,"variable":"title","value":"L'alphabet visuel"},{"id":3,"variable":"title","value":"Les outils de base"},{"id":-2,"variable":"title","value":"Communiquer mieux grâce au dessin"},{"id":4,"variable":"title","value":"Les idéogrammes"},{"id":5,"variable":"title","value":"Les modèles visuels"},{"id":6,"variable":"title","value":"Motiver les autres"},{"id":-3,"variable":"title","value":"Lancer des réunions visuelles"},{"id":7,"variable":"title","value":"Présenter ses idées avec un storyboard"},{"id":8,"variable":"title","value":"Faciliter des réunions"},{"id":9,"variable":"title","value":"Organiser des réunions visuelles"},{"id":-0,"variable":"type","value":"course"},{"id":-1,"variable":"type","value":"partie"},{"id":1,"variable":"type","value":"chapitre"},{"id":2,"variable":"type","value":"chapitre"},{"id":3,"variable":"type","value":"chapitre"},{"id":-2,"variable":"type","value":"partie"},{"id":4,"variable":"type","value":"chapitre"},{"id":5,"variable":"type","value":"chapitre"},{"id":6,"variable":"type","value":"chapitre"},{"id":-3,"variable":"type","value":"partie"},{"id":7,"variable":"type","value":"chapitre"},{"id":8,"variable":"type","value":"chapitre"},{"id":9,"variable":"type","value":"chapitre"},{"id":-0,"variable":"slug","value":"simplifiez-vos-reunions-grace-au-doodling"},{"id":-1,"variable":"slug","value":"decouvrir-les-bases-du-doodling"},{"id":1,"variable":"slug","value":"introduction-au-doodling"},{"id":2,"variable":"slug","value":"l-alphabet-visuel"},{"id":3,"variable":"slug","value":"les-outils-10"},{"id":-2,"variable":"slug","value":"communiquer-mieux-grace-au-dessin"},{"id":4,"variable":"slug","value":"les-ideogrammes"},{"id":5,"variable":"slug","value":"les-modeles-visuels"},{"id":6,"variable":"slug","value":"motiver-les-autres"},{"id":-3,"variable":"slug","value":"lancer-des-reunions-visuelles"},{"id":7,"variable":"slug","value":"presenter-ses-idees-avec-un-storyboard"},{"id":8,"variable":"slug","value":"faciliter-des-reunions"},{"id":9,"variable":"slug","value":"organiser-des-reunions-visuelles"},{"id":-0,"variable":"max.duration","value":"0"},{"id":-1,"variable":"max.duration","value":"0"},{"id":1,"variable":"max.duration","value":"567"},{"id":2,"variable":"max.duration","value":"1382.5"},{"id":3,"variable":"max.duration","value":"1149.4"},{"id":-2,"variable":"max.duration","value":"0"},{"id":4,"variable":"max.duration","value":"1159.3"},{"id":5,"variable":"max.duration","value":"1200.9"},{"id":6,"variable":"max.duration","value":"1050.6"},{"id":-3,"variable":"max.duration","value":"0"},{"id":7,"variable":"max.duration","value":"897.1"},{"id":8,"variable":"max.duration","value":"957.8"},{"id":9,"variable":"max.duration","value":"781.3"},{"id":-0,"variable":"mean.duration","value":"0"},{"id":-1,"variable":"mean.duration","value":"0"},{"id":1,"variable":"mean.duration","value":"232.68"},{"id":2,"variable":"mean.duration","value":"506.51"},{"id":3,"variable":"mean.duration","value":"411.35"},{"id":-2,"variable":"mean.duration","value":"0"},{"id":4,"variable":"mean.duration","value":"383.56"},{"id":5,"variable":"mean.duration","value":"451.41"},{"id":6,"variable":"mean.duration","value":"341.94"},{"id":-3,"variable":"mean.duration","value":"0"},{"id":7,"variable":"mean.duration","value":"329.07"},{"id":8,"variable":"mean.duration","value":"367.3"},{"id":9,"variable":"mean.duration","value":"255.66"},{"id":-0,"variable":"median.duration","value":"0"},{"id":-1,"variable":"median.duration","value":"0"},{"id":1,"variable":"median.duration","value":"184"},{"id":2,"variable":"median.duration","value":"325"},{"id":3,"variable":"median.duration","value":"264"},{"id":-2,"variable":"median.duration","value":"0"},{"id":4,"variable":"median.duration","value":"240.5"},{"id":5,"variable":"median.duration","value":"290"},{"id":6,"variable":"median.duration","value":"189"},{"id":-3,"variable":"median.duration","value":"0"},{"id":7,"variable":"median.duration","value":"240.5"},{"id":8,"variable":"median.duration","value":"259"},{"id":9,"variable":"median.duration","value":"150"},{"id":-0,"variable":"q1.duration","value":"0"},{"id":-1,"variable":"q1.duration","value":"0"},{"id":1,"variable":"q1.duration","value":"26"},{"id":2,"variable":"q1.duration","value":"76.75"},{"id":3,"variable":"q1.duration","value":"55"},{"id":-2,"variable":"q1.duration","value":"0"},{"id":4,"variable":"q1.duration","value":"34.25"},{"id":5,"variable":"q1.duration","value":"66.25"},{"id":6,"variable":"q1.duration","value":"27"},{"id":-3,"variable":"q1.duration","value":"0"},{"id":7,"variable":"q1.duration","value":"38.75"},{"id":8,"variable":"q1.duration","value":"54.25"},{"id":9,"variable":"q1.duration","value":"34.75"},{"id":-0,"variable":"q3.duration","value":"0"},{"id":-1,"variable":"q3.duration","value":"0"},{"id":1,"variable":"q3.duration","value":"238"},{"id":2,"variable":"q3.duration","value":"453.25"},{"id":3,"variable":"q3.duration","value":"392.5"},{"id":-2,"variable":"q3.duration","value":"0"},{"id":4,"variable":"q3.duration","value":"335"},{"id":5,"variable":"q3.duration","value":"410.25"},{"id":6,"variable":"q3.duration","value":"273.5"},{"id":-3,"variable":"q3.duration","value":"0"},{"id":7,"variable":"q3.duration","value":"295.25"},{"id":8,"variable":"q3.duration","value":"304.5"},{"id":9,"variable":"q3.duration","value":"204.25"},{"id":-0,"variable":"size","value":"0"},{"id":-1,"variable":"size","value":"1605"},{"id":1,"variable":"size","value":"459"},{"id":2,"variable":"size","value":"626"},{"id":3,"variable":"size","value":"520"},{"id":-2,"variable":"size","value":"1428"},{"id":4,"variable":"size","value":"502"},{"id":5,"variable":"size","value":"552"},{"id":6,"variable":"size","value":"374"},{"id":-3,"variable":"size","value":"1315"},{"id":7,"variable":"size","value":"523"},{"id":8,"variable":"size","value":"504"},{"id":9,"variable":"size","value":"288"},{"id":-0,"variable":"speed","value":"-1"},{"id":-1,"variable":"speed","value":"-1"},{"id":1,"variable":"speed","value":"118.36"},{"id":2,"variable":"speed","value":"74.15"},{"id":3,"variable":"speed","value":"75.85"},{"id":-2,"variable":"speed","value":"-1"},{"id":4,"variable":"speed","value":"78.53"},{"id":5,"variable":"speed","value":"73.37"},{"id":6,"variable":"speed","value":"65.63"},{"id":-3,"variable":"speed","value":"-1"},{"id":7,"variable":"speed","value":"95.36"},{"id":8,"variable":"speed","value":"82.33"},{"id":9,"variable":"speed","value":"67.59"},{"id":-0,"variable":"interest","value":"0.0491947391964226"},{"id":-1,"variable":"interest","value":"-1"},{"id":1,"variable":"interest","value":"0.339584293175119"},{"id":2,"variable":"interest","value":"1"},{"id":3,"variable":"interest","value":"0.794553705440903"},{"id":-2,"variable":"interest","value":"-1"},{"id":4,"variable":"interest","value":"0.534968640026781"},{"id":5,"variable":"interest","value":"0.458069302533936"},{"id":6,"variable":"interest","value":"0.547325898630356"},{"id":-3,"variable":"interest","value":"-1"},{"id":7,"variable":"interest","value":"0"},{"id":8,"variable":"interest","value":"0.12682126719037"},{"id":9,"variable":"interest","value":"0.369907802068584"},{"id":-0,"variable":"Actions_nb","value":"0"},{"id":-1,"variable":"Actions_nb","value":"0"},{"id":1,"variable":"Actions_nb","value":"1679"},{"id":2,"variable":"Actions_nb","value":"1327"},{"id":3,"variable":"Actions_nb","value":"1324"},{"id":-2,"variable":"Actions_nb","value":"0"},{"id":4,"variable":"Actions_nb","value":"996"},{"id":5,"variable":"Actions_nb","value":"700"},{"id":6,"variable":"Actions_nb","value":"747"},{"id":-3,"variable":"Actions_nb","value":"0"},{"id":7,"variable":"Actions_nb","value":"715"},{"id":8,"variable":"Actions_nb","value":"461"},{"id":9,"variable":"Actions_nb","value":"581"},{"id":-0,"variable":"Readers","value":"1067"},{"id":-1,"variable":"Readers","value":"0"},{"id":1,"variable":"Readers","value":"906"},{"id":2,"variable":"Readers","value":"800"},{"id":3,"variable":"Readers","value":"651"},{"id":-2,"variable":"Readers","value":"0"},{"id":4,"variable":"Readers","value":"493"},{"id":5,"variable":"Readers","value":"382"},{"id":6,"variable":"Readers","value":"333"},{"id":-3,"variable":"Readers","value":"0"},{"id":7,"variable":"Readers","value":"334"},{"id":8,"variable":"Readers","value":"279"},{"id":9,"variable":"Readers","value":"246"},{"id":-0,"variable":"Rereaders","value":"0"},{"id":-1,"variable":"Rereaders","value":"NaN"},{"id":1,"variable":"Rereaders","value":"372"},{"id":2,"variable":"Rereaders","value":"285"},{"id":3,"variable":"Rereaders","value":"290"},{"id":-2,"variable":"Rereaders","value":"NaN"},{"id":4,"variable":"Rereaders","value":"234"},{"id":5,"variable":"Rereaders","value":"161"},{"id":6,"variable":"Rereaders","value":"161"},{"id":-3,"variable":"Rereaders","value":"NaN"},{"id":7,"variable":"Rereaders","value":"169"},{"id":8,"variable":"Rereaders","value":"110"},{"id":9,"variable":"Rereaders","value":"139"},{"id":-0,"variable":"Readings","value":"0"},{"id":-1,"variable":"Readings","value":"NaN"},{"id":1,"variable":"Readings","value":"1679"},{"id":2,"variable":"Readings","value":"1327"},{"id":3,"variable":"Readings","value":"1324"},{"id":-2,"variable":"Readings","value":"NaN"},{"id":4,"variable":"Readings","value":"996"},{"id":5,"variable":"Readings","value":"700"},{"id":6,"variable":"Readings","value":"747"},{"id":-3,"variable":"Readings","value":"NaN"},{"id":7,"variable":"Readings","value":"715"},{"id":8,"variable":"Readings","value":"461"},{"id":9,"variable":"Readings","value":"581"},{"id":-0,"variable":"readers_tx","value":"1"},{"id":-1,"variable":"readers_tx","value":"0"},{"id":1,"variable":"readers_tx","value":"0.849109653233365"},{"id":2,"variable":"readers_tx","value":"0.749765698219306"},{"id":3,"variable":"readers_tx","value":"0.610121836925961"},{"id":-2,"variable":"readers_tx","value":"0"},{"id":4,"variable":"readers_tx","value":"0.462043111527648"},{"id":5,"variable":"readers_tx","value":"0.358013120899719"},{"id":6,"variable":"readers_tx","value":"0.312089971883786"},{"id":-3,"variable":"readers_tx","value":"0"},{"id":7,"variable":"readers_tx","value":"0.31302717900656"},{"id":8,"variable":"readers_tx","value":"0.261480787253983"},{"id":9,"variable":"readers_tx","value":"0.230552952202437"},{"id":-0,"variable":"Actions_tx","value":"0"},{"id":-1,"variable":"Actions_tx","value":"0"},{"id":1,"variable":"Actions_tx","value":"0.1968347010551"},{"id":2,"variable":"Actions_tx","value":"0.15556858147714"},{"id":3,"variable":"Actions_tx","value":"0.155216881594373"},{"id":-2,"variable":"Actions_tx","value":"0"},{"id":4,"variable":"Actions_tx","value":"0.116764361078546"},{"id":5,"variable":"Actions_tx","value":"0.082063305978898"},{"id":6,"variable":"Actions_tx","value":"0.0875732708089097"},{"id":-3,"variable":"Actions_tx","value":"0"},{"id":7,"variable":"Actions_tx","value":"0.0838218053927315"},{"id":8,"variable":"Actions_tx","value":"0.0540445486518171"},{"id":9,"variable":"Actions_tx","value":"0.0681125439624853"},{"id":-0,"variable":"rs_tx","value":"1"},{"id":-1,"variable":"rs_tx","value":"0"},{"id":1,"variable":"rs_tx","value":"0.442901770218674"},{"id":2,"variable":"rs_tx","value":"0.367927802846234"},{"id":3,"variable":"rs_tx","value":"0.333217632766401"},{"id":-2,"variable":"rs_tx","value":"0"},{"id":4,"variable":"rs_tx","value":"0.271086428323499"},{"id":5,"variable":"rs_tx","value":"0.19993057965984"},{"id":6,"variable":"rs_tx","value":"0.188823325234294"},{"id":-3,"variable":"rs_tx","value":"0"},{"id":7,"variable":"rs_tx","value":"0.201318986463034"},{"id":8,"variable":"rs_tx","value":"0.13328705310656"},{"id":9,"variable":"rs_tx","value":"0.12912183269698"},{"id":-0,"variable":"Rereadings","value":"0"},{"id":-1,"variable":"Rereadings","value":"NaN"},{"id":1,"variable":"Rereadings","value":"650"},{"id":2,"variable":"Rereadings","value":"460"},{"id":3,"variable":"Rereadings","value":"557"},{"id":-2,"variable":"Rereadings","value":"NaN"},{"id":4,"variable":"Rereadings","value":"445"},{"id":5,"variable":"Rereadings","value":"291"},{"id":6,"variable":"Rereadings","value":"347"},{"id":-3,"variable":"Rereadings","value":"NaN"},{"id":7,"variable":"Rereadings","value":"342"},{"id":8,"variable":"Rereadings","value":"165"},{"id":9,"variable":"Rereadings","value":"265"},{"id":-0,"variable":"rereads_tx","value":"0"},{"id":-1,"variable":"rereads_tx","value":"0.384825544928376"},{"id":1,"variable":"rereads_tx","value":"0.387135199523526"},{"id":2,"variable":"rereads_tx","value":"0.346646571213263"},{"id":3,"variable":"rereads_tx","value":"0.420694864048338"},{"id":-2,"variable":"rereads_tx","value":"0.442342066679416"},{"id":4,"variable":"rereads_tx","value":"0.446787148594378"},{"id":5,"variable":"rereads_tx","value":"0.415714285714286"},{"id":6,"variable":"rereads_tx","value":"0.464524765729585"},{"id":-3,"variable":"rereads_tx","value":"0.43078313457531"},{"id":7,"variable":"rereads_tx","value":"0.478321678321678"},{"id":8,"variable":"rereads_tx","value":"0.357917570498915"},{"id":9,"variable":"rereads_tx","value":"0.456110154905336"},{"id":-0,"variable":"rereads_globratio","value":"0"},{"id":-1,"variable":"rereads_globratio","value":"0.157770206322165"},{"id":1,"variable":"rereads_globratio","value":"0.184554230550823"},{"id":2,"variable":"rereads_globratio","value":"0.13060760931289"},{"id":3,"variable":"rereads_globratio","value":"0.158148779102783"},{"id":-2,"variable":"rereads_globratio","value":"0.102498580352073"},{"id":4,"variable":"rereads_globratio","value":"0.126348665530948"},{"id":5,"variable":"rereads_globratio","value":"0.0826235093696763"},{"id":6,"variable":"rereads_globratio","value":"0.0985235661555934"},{"id":-3,"variable":"rereads_globratio","value":"0.0730645466590952"},{"id":7,"variable":"rereads_globratio","value":"0.0971039182282794"},{"id":8,"variable":"rereads_globratio","value":"0.0468483816013629"},{"id":9,"variable":"rereads_globratio","value":"0.0752413401476434"},{"id":-0,"variable":"rereads_seq_tx","value":"0.395303754116075"},{"id":-1,"variable":"rereads_seq_tx","value":"0.436931403101101"},{"id":1,"variable":"rereads_seq_tx","value":"0.430769230769231"},{"id":2,"variable":"rereads_seq_tx","value":"0.434782608695652"},{"id":3,"variable":"rereads_seq_tx","value":"0.44524236983842"},{"id":-2,"variable":"rereads_seq_tx","value":"0.359357719277416"},{"id":4,"variable":"rereads_seq_tx","value":"0.352808988764045"},{"id":5,"variable":"rereads_seq_tx","value":"0.333333333333333"},{"id":6,"variable":"rereads_seq_tx","value":"0.39193083573487"},{"id":-3,"variable":"rereads_seq_tx","value":"0.389622139969707"},{"id":7,"variable":"rereads_seq_tx","value":"0.280701754385965"},{"id":8,"variable":"rereads_seq_tx","value":"0.363636363636364"},{"id":9,"variable":"rereads_seq_tx","value":"0.524528301886792"},{"id":-0,"variable":"rereads_seq_globratio","value":"0.111111111111111"},{"id":-1,"variable":"rereads_seq_globratio","value":"0"},{"id":1,"variable":"rereads_seq_globratio","value":"0.198159943382873"},{"id":2,"variable":"rereads_seq_globratio","value":"0.141542816702052"},{"id":3,"variable":"rereads_seq_globratio","value":"0.175513092710545"},{"id":-2,"variable":"rereads_seq_globratio","value":"0"},{"id":4,"variable":"rereads_seq_globratio","value":"0.111111111111111"},{"id":5,"variable":"rereads_seq_globratio","value":"0.0686482661004954"},{"id":6,"variable":"rereads_seq_globratio","value":"0.0962491153573956"},{"id":-3,"variable":"rereads_seq_globratio","value":"0"},{"id":7,"variable":"rereads_seq_globratio","value":"0.0679405520169851"},{"id":8,"variable":"rereads_seq_globratio","value":"0.0424628450106157"},{"id":9,"variable":"rereads_seq_globratio","value":"0.0983722576079264"},{"id":-0,"variable":"rereads_dec_tx","value":"0.604696245883925"},{"id":-1,"variable":"rereads_dec_tx","value":"0.563068596898899"},{"id":1,"variable":"rereads_dec_tx","value":"0.569230769230769"},{"id":2,"variable":"rereads_dec_tx","value":"0.565217391304348"},{"id":3,"variable":"rereads_dec_tx","value":"0.55475763016158"},{"id":-2,"variable":"rereads_dec_tx","value":"0.640642280722584"},{"id":4,"variable":"rereads_dec_tx","value":"0.647191011235955"},{"id":5,"variable":"rereads_dec_tx","value":"0.666666666666667"},{"id":6,"variable":"rereads_dec_tx","value":"0.60806916426513"},{"id":-3,"variable":"rereads_dec_tx","value":"0.610377860030293"},{"id":7,"variable":"rereads_dec_tx","value":"0.719298245614035"},{"id":8,"variable":"rereads_dec_tx","value":"0.636363636363636"},{"id":9,"variable":"rereads_dec_tx","value":"0.475471698113208"},{"id":-0,"variable":"rereads_dec_globratio","value":"0.111111111111111"},{"id":-1,"variable":"rereads_dec_globratio","value":"0.148411569464201"},{"id":1,"variable":"rereads_dec_globratio","value":"0.175438596491228"},{"id":2,"variable":"rereads_dec_globratio","value":"0.123281175912755"},{"id":3,"variable":"rereads_dec_globratio","value":"0.14651493598862"},{"id":-2,"variable":"rereads_dec_globratio","value":"0.109530583214794"},{"id":4,"variable":"rereads_dec_globratio","value":"0.136557610241821"},{"id":5,"variable":"rereads_dec_globratio","value":"0.0919867235656709"},{"id":6,"variable":"rereads_dec_globratio","value":"0.10004741583689"},{"id":-3,"variable":"rereads_dec_globratio","value":"0.0753911806543385"},{"id":7,"variable":"rereads_dec_globratio","value":"0.116642958748222"},{"id":8,"variable":"rereads_dec_globratio","value":"0.0497866287339972"},{"id":9,"variable":"rereads_dec_globratio","value":"0.0597439544807966"},{"id":-0,"variable":"Sequential_rereadings","value":"0"},{"id":-1,"variable":"Sequential_rereadings","value":"0"},{"id":1,"variable":"Sequential_rereadings","value":"280"},{"id":2,"variable":"Sequential_rereadings","value":"200"},{"id":3,"variable":"Sequential_rereadings","value":"248"},{"id":-2,"variable":"Sequential_rereadings","value":"0"},{"id":4,"variable":"Sequential_rereadings","value":"157"},{"id":5,"variable":"Sequential_rereadings","value":"97"},{"id":6,"variable":"Sequential_rereadings","value":"136"},{"id":-3,"variable":"Sequential_rereadings","value":"0"},{"id":7,"variable":"Sequential_rereadings","value":"96"},{"id":8,"variable":"Sequential_rereadings","value":"60"},{"id":9,"variable":"Sequential_rereadings","value":"139"},{"id":-0,"variable":"Decaled_rereadings","value":"0"},{"id":-1,"variable":"Decaled_rereadings","value":"0"},{"id":1,"variable":"Decaled_rereadings","value":"370"},{"id":2,"variable":"Decaled_rereadings","value":"260"},{"id":3,"variable":"Decaled_rereadings","value":"309"},{"id":-2,"variable":"Decaled_rereadings","value":"0"},{"id":4,"variable":"Decaled_rereadings","value":"288"},{"id":5,"variable":"Decaled_rereadings","value":"194"},{"id":6,"variable":"Decaled_rereadings","value":"211"},{"id":-3,"variable":"Decaled_rereadings","value":"0"},{"id":7,"variable":"Decaled_rereadings","value":"246"},{"id":8,"variable":"Decaled_rereadings","value":"105"},{"id":9,"variable":"Decaled_rereadings","value":"126"},{"id":-0,"variable":"rereads_tx.1","value":"0"},{"id":-1,"variable":"rereads_tx.1","value":"0.384825544928376"},{"id":1,"variable":"rereads_tx.1","value":"0.387135199523526"},{"id":2,"variable":"rereads_tx.1","value":"0.346646571213263"},{"id":3,"variable":"rereads_tx.1","value":"0.420694864048338"},{"id":-2,"variable":"rereads_tx.1","value":"0.442342066679416"},{"id":4,"variable":"rereads_tx.1","value":"0.446787148594378"},{"id":5,"variable":"rereads_tx.1","value":"0.415714285714286"},{"id":6,"variable":"rereads_tx.1","value":"0.464524765729585"},{"id":-3,"variable":"rereads_tx.1","value":"0.43078313457531"},{"id":7,"variable":"rereads_tx.1","value":"0.478321678321678"},{"id":8,"variable":"rereads_tx.1","value":"0.357917570498915"},{"id":9,"variable":"rereads_tx.1","value":"0.456110154905336"},{"id":-0,"variable":"part_readers_rereaders","value":"0"},{"id":-1,"variable":"part_readers_rereaders","value":"NaN"},{"id":1,"variable":"part_readers_rereaders","value":"0.4106"},{"id":2,"variable":"part_readers_rereaders","value":"0.3562"},{"id":3,"variable":"part_readers_rereaders","value":"0.4455"},{"id":-2,"variable":"part_readers_rereaders","value":"NaN"},{"id":4,"variable":"part_readers_rereaders","value":"0.4746"},{"id":5,"variable":"part_readers_rereaders","value":"0.4215"},{"id":6,"variable":"part_readers_rereaders","value":"0.4835"},{"id":-3,"variable":"part_readers_rereaders","value":"NaN"},{"id":7,"variable":"part_readers_rereaders","value":"0.506"},{"id":8,"variable":"part_readers_rereaders","value":"0.3943"},{"id":9,"variable":"part_readers_rereaders","value":"0.565"},{"id":-0,"variable":"course_readers_rereaders","value":"0"},{"id":-1,"variable":"course_readers_rereaders","value":"NaN"},{"id":1,"variable":"course_readers_rereaders","value":"0.3486"},{"id":2,"variable":"course_readers_rereaders","value":"0.2671"},{"id":3,"variable":"course_readers_rereaders","value":"0.2718"},{"id":-2,"variable":"course_readers_rereaders","value":"NaN"},{"id":4,"variable":"course_readers_rereaders","value":"0.2193"},{"id":5,"variable":"course_readers_rereaders","value":"0.1509"},{"id":6,"variable":"course_readers_rereaders","value":"0.1509"},{"id":-3,"variable":"course_readers_rereaders","value":"NaN"},{"id":7,"variable":"course_readers_rereaders","value":"0.1584"},{"id":8,"variable":"course_readers_rereaders","value":"0.1031"},{"id":9,"variable":"course_readers_rereaders","value":"0.1303"},{"id":-0,"variable":"reading_not_linear","value":"0.37177806609665"},{"id":-1,"variable":"reading_not_linear","value":"0"},{"id":1,"variable":"reading_not_linear","value":"0.943011618722272"},{"id":2,"variable":"reading_not_linear","value":"0.0355637311169382"},{"id":3,"variable":"reading_not_linear","value":"0.281815178866195"},{"id":-2,"variable":"reading_not_linear","value":"0"},{"id":4,"variable":"reading_not_linear","value":"0.338044583119244"},{"id":5,"variable":"reading_not_linear","value":"0.0319510087756937"},{"id":6,"variable":"reading_not_linear","value":"0.305742017837126"},{"id":-3,"variable":"reading_not_linear","value":"0"},{"id":7,"variable":"reading_not_linear","value":"0.409874456432384"},{"id":8,"variable":"reading_not_linear","value":"0"},{"id":9,"variable":"reading_not_linear","value":"1"},{"id":-0,"variable":"provenance_prev","value":"0.683663805545777"},{"id":-1,"variable":"provenance_prev","value":"0"},{"id":1,"variable":"provenance_prev","value":"0"},{"id":2,"variable":"provenance_prev","value":"0.830827067669173"},{"id":3,"variable":"provenance_prev","value":"0.778443113772455"},{"id":-2,"variable":"provenance_prev","value":"0"},{"id":4,"variable":"provenance_prev","value":"0.684010152284264"},{"id":5,"variable":"provenance_prev","value":"0.846551724137931"},{"id":6,"variable":"provenance_prev","value":"0.724612736660929"},{"id":-3,"variable":"provenance_prev","value":"0"},{"id":7,"variable":"provenance_prev","value":"0.631858407079646"},{"id":8,"variable":"provenance_prev","value":"0.838235294117647"},{"id":9,"variable":"provenance_prev","value":"0.818435754189944"},{"id":-0,"variable":"provenance_not_linear","value":"0.316336194454223"},{"id":-1,"variable":"provenance_not_linear","value":"0"},{"id":1,"variable":"provenance_not_linear","value":"1"},{"id":2,"variable":"provenance_not_linear","value":"0.169172932330827"},{"id":3,"variable":"provenance_not_linear","value":"0.221556886227545"},{"id":-2,"variable":"provenance_not_linear","value":"0"},{"id":4,"variable":"provenance_not_linear","value":"0.315989847715736"},{"id":5,"variable":"provenance_not_linear","value":"0.153448275862069"},{"id":6,"variable":"provenance_not_linear","value":"0.275387263339071"},{"id":-3,"variable":"provenance_not_linear","value":"0"},{"id":7,"variable":"provenance_not_linear","value":"0.368141592920354"},{"id":8,"variable":"provenance_not_linear","value":"0.161764705882353"},{"id":9,"variable":"provenance_not_linear","value":"0.181564245810056"},{"id":-0,"variable":"provenance_past","value":"0.0788076392424606"},{"id":-1,"variable":"provenance_past","value":"0"},{"id":1,"variable":"provenance_past","value":"0"},{"id":2,"variable":"provenance_past","value":"0"},{"id":3,"variable":"provenance_past","value":"0.0479041916167665"},{"id":-2,"variable":"provenance_past","value":"0"},{"id":4,"variable":"provenance_past","value":"0.109137055837563"},{"id":5,"variable":"provenance_past","value":"0.0431034482758621"},{"id":6,"variable":"provenance_past","value":"0.101549053356282"},{"id":-3,"variable":"provenance_past","value":"0"},{"id":7,"variable":"provenance_past","value":"0.176991150442478"},{"id":8,"variable":"provenance_past","value":"0.0490196078431373"},{"id":9,"variable":"provenance_past","value":"0.181564245810056"},{"id":-0,"variable":"provenance_future","value":"0.237528555211763"},{"id":-1,"variable":"provenance_future","value":"0"},{"id":1,"variable":"provenance_future","value":"1"},{"id":2,"variable":"provenance_future","value":"0.169172932330827"},{"id":3,"variable":"provenance_future","value":"0.173652694610778"},{"id":-2,"variable":"provenance_future","value":"0"},{"id":4,"variable":"provenance_future","value":"0.206852791878173"},{"id":5,"variable":"provenance_future","value":"0.110344827586207"},{"id":6,"variable":"provenance_future","value":"0.173838209982788"},{"id":-3,"variable":"provenance_future","value":"0"},{"id":7,"variable":"provenance_future","value":"0.191150442477876"},{"id":8,"variable":"provenance_future","value":"0.112745098039216"},{"id":9,"variable":"provenance_future","value":"0"},{"id":-0,"variable":"destination_next","value":"0.657096954278254"},{"id":-1,"variable":"destination_next","value":"0"},{"id":1,"variable":"destination_next","value":"0.865817825661117"},{"id":2,"variable":"destination_next","value":"0.789473684210526"},{"id":3,"variable":"destination_next","value":"0.637115839243499"},{"id":-2,"variable":"destination_next","value":"0"},{"id":4,"variable":"destination_next","value":"0.684797768479777"},{"id":5,"variable":"destination_next","value":"0.776752767527675"},{"id":6,"variable":"destination_next","value":"0.671052631578947"},{"id":-3,"variable":"destination_next","value":"0"},{"id":7,"variable":"destination_next","value":"0.677227722772277"},{"id":8,"variable":"destination_next","value":"0.811634349030471"},{"id":9,"variable":"destination_next","value":"0"},{"id":-0,"variable":"destination_not_linear","value":"0.342903045721746"},{"id":-1,"variable":"destination_not_linear","value":"0"},{"id":1,"variable":"destination_not_linear","value":"0.134182174338883"},{"id":2,"variable":"destination_not_linear","value":"0.210526315789474"},{"id":3,"variable":"destination_not_linear","value":"0.362884160756501"},{"id":-2,"variable":"destination_not_linear","value":"0"},{"id":4,"variable":"destination_not_linear","value":"0.315202231520223"},{"id":5,"variable":"destination_not_linear","value":"0.223247232472325"},{"id":6,"variable":"destination_not_linear","value":"0.328947368421053"},{"id":-3,"variable":"destination_not_linear","value":"0"},{"id":7,"variable":"destination_not_linear","value":"0.322772277227723"},{"id":8,"variable":"destination_not_linear","value":"0.188365650969529"},{"id":9,"variable":"destination_not_linear","value":"1"},{"id":-0,"variable":"destination_past","value":"0.287241256949645"},{"id":-1,"variable":"destination_past","value":"0"},{"id":1,"variable":"destination_past","value":"0"},{"id":2,"variable":"destination_past","value":"0.15080971659919"},{"id":3,"variable":"destination_past","value":"0.275413711583924"},{"id":-2,"variable":"destination_past","value":"0"},{"id":4,"variable":"destination_past","value":"0.224546722454672"},{"id":5,"variable":"destination_past","value":"0.180811808118081"},{"id":6,"variable":"destination_past","value":"0.280075187969925"},{"id":-3,"variable":"destination_past","value":"0"},{"id":7,"variable":"destination_past","value":"0.285148514851485"},{"id":8,"variable":"destination_past","value":"0.188365650969529"},{"id":9,"variable":"destination_past","value":"1"},{"id":-0,"variable":"destination_future","value":"0.0556617887721004"},{"id":-1,"variable":"destination_future","value":"0"},{"id":1,"variable":"destination_future","value":"0.134182174338883"},{"id":2,"variable":"destination_future","value":"0.0597165991902834"},{"id":3,"variable":"destination_future","value":"0.0874704491725768"},{"id":-2,"variable":"destination_future","value":"0"},{"id":4,"variable":"destination_future","value":"0.0906555090655509"},{"id":5,"variable":"destination_future","value":"0.0424354243542435"},{"id":6,"variable":"destination_future","value":"0.0488721804511278"},{"id":-3,"variable":"destination_future","value":"0"},{"id":7,"variable":"destination_future","value":"0.0376237623762376"},{"id":8,"variable":"destination_future","value":"0"},{"id":9,"variable":"destination_future","value":"0"},{"id":-0,"variable":"rupture_tx","value":"1"},{"id":-1,"variable":"rupture_tx","value":"0.810536980749747"},{"id":1,"variable":"rupture_tx","value":"0.448328267477204"},{"id":2,"variable":"rupture_tx","value":"0.217071935157042"},{"id":3,"variable":"rupture_tx","value":"0.145136778115502"},{"id":-2,"variable":"rupture_tx","value":"0.149696048632219"},{"id":4,"variable":"rupture_tx","value":"0.0795339412360689"},{"id":5,"variable":"rupture_tx","value":"0.0400202634245187"},{"id":6,"variable":"rupture_tx","value":"0.0301418439716312"},{"id":-3,"variable":"rupture_tx","value":"0.0397669706180344"},{"id":7,"variable":"rupture_tx","value":"0.0238095238095238"},{"id":8,"variable":"rupture_tx","value":"0.00835866261398176"},{"id":9,"variable":"rupture_tx","value":"0.00759878419452888"},{"id":-0,"variable":"norecovery_tx","value":"1"},{"id":-1,"variable":"norecovery_tx","value":"0.849109653233365"},{"id":1,"variable":"norecovery_tx","value":"0.509840674789128"},{"id":2,"variable":"norecovery_tx","value":"0.209934395501406"},{"id":3,"variable":"norecovery_tx","value":"0.12933458294283"},{"id":-2,"variable":"norecovery_tx","value":"0.115276476101218"},{"id":4,"variable":"norecovery_tx","value":"0.0646672914714152"},{"id":5,"variable":"norecovery_tx","value":"0.0328022492970947"},{"id":6,"variable":"norecovery_tx","value":"0.0178069353327085"},{"id":-3,"variable":"norecovery_tx","value":"0.0356138706654171"},{"id":7,"variable":"norecovery_tx","value":"0.0234301780693533"},{"id":8,"variable":"norecovery_tx","value":"0.00656044985941893"},{"id":9,"variable":"norecovery_tx","value":"0.0056232427366448"},{"id":-0,"variable":"resume_abnormal_tx","value":"0.288313120176406"},{"id":-1,"variable":"resume_abnormal_tx","value":"0.280259365994236"},{"id":1,"variable":"resume_abnormal_tx","value":"0.241935483870968"},{"id":2,"variable":"resume_abnormal_tx","value":"0.310513447432763"},{"id":3,"variable":"resume_abnormal_tx","value":"0.326599326599327"},{"id":-2,"variable":"resume_abnormal_tx","value":"0.301449275362319"},{"id":4,"variable":"resume_abnormal_tx","value":"0.295454545454545"},{"id":5,"variable":"resume_abnormal_tx","value":"0.272727272727273"},{"id":6,"variable":"resume_abnormal_tx","value":"0.345679012345679"},{"id":-3,"variable":"resume_abnormal_tx","value":"0.37037037037037"},{"id":7,"variable":"resume_abnormal_tx","value":"0.340909090909091"},{"id":8,"variable":"resume_abnormal_tx","value":"0.578947368421053"},{"id":9,"variable":"resume_abnormal_tx","value":"0.222222222222222"},{"id":-0,"variable":"resume_past","value":"0.209481808158765"},{"id":-1,"variable":"resume_past","value":"0.207492795389049"},{"id":1,"variable":"resume_past","value":"0.178885630498534"},{"id":2,"variable":"resume_past","value":"0.234718826405868"},{"id":3,"variable":"resume_past","value":"0.235690235690236"},{"id":-2,"variable":"resume_past","value":"0.208695652173913"},{"id":4,"variable":"resume_past","value":"0.210227272727273"},{"id":5,"variable":"resume_past","value":"0.204545454545455"},{"id":6,"variable":"resume_past","value":"0.209876543209877"},{"id":-3,"variable":"resume_past","value":"0.246913580246914"},{"id":7,"variable":"resume_past","value":"0.227272727272727"},{"id":8,"variable":"resume_past","value":"0.315789473684211"},{"id":9,"variable":"resume_past","value":"0.222222222222222"},{"id":-0,"variable":"resume_future","value":"0.0788313120176406"},{"id":-1,"variable":"resume_future","value":"0.0727665706051873"},{"id":1,"variable":"resume_future","value":"0.063049853372434"},{"id":2,"variable":"resume_future","value":"0.0757946210268949"},{"id":3,"variable":"resume_future","value":"0.0909090909090909"},{"id":-2,"variable":"resume_future","value":"0.0927536231884058"},{"id":4,"variable":"resume_future","value":"0.0852272727272727"},{"id":5,"variable":"resume_future","value":"0.0681818181818182"},{"id":6,"variable":"resume_future","value":"0.135802469135802"},{"id":-3,"variable":"resume_future","value":"0.123456790123457"},{"id":7,"variable":"resume_future","value":"0.113636363636364"},{"id":8,"variable":"resume_future","value":"0.263157894736842"},{"id":9,"variable":"resume_future","value":"0"},{"id":-0,"variable":"tome_index","value":"0"},{"id":-1,"variable":"tome_index","value":"1"},{"id":1,"variable":"tome_index","value":"0"},{"id":2,"variable":"tome_index","value":"0"},{"id":3,"variable":"tome_index","value":"0"},{"id":-2,"variable":"tome_index","value":"2"},{"id":4,"variable":"tome_index","value":"0"},{"id":5,"variable":"tome_index","value":"0"},{"id":6,"variable":"tome_index","value":"0"},{"id":-3,"variable":"tome_index","value":"3"},{"id":7,"variable":"tome_index","value":"0"},{"id":8,"variable":"tome_index","value":"0"},{"id":9,"variable":"tome_index","value":"0"},{"id":0,"variable":"title","value":"Simplifiez vos réunions grâce au Doodling"},{"id":0,"variable":"nactions","value":"8530"},{"id":0,"variable":"nusers","value":"1067"},{"id":0,"variable":"nRS","value":"2881"},{"id":0,"variable":"RS_meanparts","value":"2.26761541131552"},{"id":0,"variable":"RS_meanperuser","value":"2.70009372071228"},{"id":0,"variable":"ob_begin","value":"2014-10-31 20:42:41"},{"id":0,"variable":"ob_end","value":"2016-07-07 00:32:24"}]