[{"part_id":853441,"value":0.6589,"classe":"rereads_tx","issueCode":"max","delta":0.089,"error_value":1.16},{"part_id":854659,"value":0.6897,"classe":"rereads_tx","issueCode":"max","delta":0.1198,"error_value":1.21},{"part_id":853441,"value":0.0996,"classe":"rereads_dec_tx","issueCode":"max","delta":0.0416,"error_value":1.72},{"part_id":854659,"value":0.1137,"classe":"rereads_dec_tx","issueCode":"max","delta":0.0556,"error_value":1.96},{"part_id":853441,"value":0.1005,"classe":"rereads_seq_tx","issueCode":"max","delta":0.0457,"error_value":1.83},{"part_id":850854,"value":0.7939,"classe":"reading_not_linear","issueCode":"max","delta":0.7939,"error_value":79.39},{"part_id":856923,"value":0.6722,"classe":"reading_not_linear","issueCode":"max","delta":0.6722,"error_value":67.22},{"part_id":857445,"value":1,"classe":"reading_not_linear","issueCode":"max","delta":1,"error_value":100},{"part_id":850854,"value":1,"classe":"provenance_not_linear","issueCode":"max","delta":1,"error_value":100},{"part_id":853441,"value":0.5151,"classe":"provenance_not_linear","issueCode":"max","delta":0.5151,"error_value":51.51},{"part_id":856923,"value":0.6334,"classe":"provenance_not_linear","issueCode":"max","delta":0.6334,"error_value":63.34},{"part_id":855044,"value":0.5653,"classe":"destination_not_linear","issueCode":"TransDestShift","delta":0.5653,"error_value":56.53},{"part_id":857445,"value":1,"classe":"destination_not_linear","issueCode":"TransDestShift","delta":1,"error_value":100},{"part_id":857445,"value":1,"classe":"destination_past","issueCode":"max","delta":1,"error_value":100},{"part_id":850854,"value":0.1616,"classe":"rupture_tx","issueCode":"max","delta":16.16,"error_value":16.16},{"part_id":851033,"value":0.1318,"classe":"rupture_tx","issueCode":"max","delta":13.18,"error_value":13.18},{"part_id":851376,"value":0.123,"classe":"rupture_tx","issueCode":"max","delta":12.3,"error_value":12.3},{"part_id":850854,"value":0.2108,"classe":"norecovery_tx","issueCode":"max","delta":0.1609,"error_value":21.08},{"part_id":851033,"value":0.1358,"classe":"norecovery_tx","issueCode":"max","delta":0.0859,"error_value":13.58},{"part_id":851376,"value":0.1018,"classe":"norecovery_tx","issueCode":"max","delta":0.0519,"error_value":10.18},{"part_id":854659,"value":0.078,"classe":"norecovery_tx","issueCode":"max","delta":0.0282,"error_value":7.8},{"part_id":856923,"value":0.3323,"classe":"resume_past","issueCode":"max","delta":0.3323,"error_value":33.23}]